{
	"format_version": "1.8.0",
	"animations": {
		"fly_left": {
			"loop": true,
			"bones": {
				"body": {
					"rotation": {
						"vector": [18.88172, -6.71771, 18.88172]
					},
					"position": {
						"vector": [0, 0, 0]
					},
					"scale": {
						"vector": [1, 1, 1]
					}
				},
				"head": {
					"position": {
						"vector": [0, 0, 0]
					},
					"scale": {
						"vector": [1, 1, 1]
					}
				},
				"torso": {
					"rotation": {
						"vector": [0, 0, 0]
					},
					"position": {
						"vector": [0, 0, 0]
					},
					"scale": {
						"vector": [1, 1, 1]
					}
				},
				"right_arm": {
					"rotation": {
						"vector": [17.44447, 8.94248, 13.2712]
					},
					"position": {
						"vector": [0, 0, 0]
					},
					"scale": {
						"vector": [1, 1, 1]
					}
				},
				"left_arm": {
					"rotation": {
						"vector": [-13.44746, 1.06062, -36.26751]
					},
					"position": {
						"vector": [0, 0, 0]
					},
					"scale": {
						"vector": [1, 1, 1]
					}
				},
				"right_leg": {
					"rotation": {
						"vector": [-4.98107, 0.43523, 4.98107]
					},
					"position": {
						"vector": [0, 0, 0]
					},
					"scale": {
						"vector": [1, 1, 1]
					}
				},
				"left_leg": {
					"rotation": {
						"vector": [12.5, 0, 0]
					},
					"position": {
						"vector": [0, 4, -4]
					},
					"scale": {
						"vector": [1, 1, 1]
					}
				}
			}
		}
	},
	"geckolib_format_version": 2
}